{
    "events": {
        "turn_0": {
            "O": {
                "labels": [
                    [
                        "O",
                        "O",
                        "O",
                        "O",
                        "O",
                        "O",
                        "O",
                        "O",
                        "O",
                        "O",
                        "O",
                        "O",
                        "O"
                    ]
                ],
                "triggers": [
                    ""
                ],
                "extras": [
                    ""
                ]
            }
        },
        "turn_1": {
            "O": {
                "labels": [
                    [
                        "O",
                        "O",
                        "O",
                        "O",
                        "O",
                        "O",
                        "O",
                        "O"
                    ]
                ],
                "triggers": [
                    ""
                ],
                "extras": [
                    ""
                ]
            }
        },
        "turn_2": {
            "O": {
                "labels": [
                    [
                        "O"
                    ]
                ],
                "triggers": [
                    ""
                ],
                "extras": [
                    ""
                ]
            }
        },
        "turn_3": {
            "O": {
                "labels": [
                    [
                        "O"
                    ]
                ],
                "triggers": [
                    ""
                ],
                "extras": [
                    ""
                ]
            }
        },
        "turn_4": {
            "O": {
                "labels": [
                    [
                        "O"
                    ]
                ],
                "triggers": [
                    ""
                ],
                "extras": [
                    ""
                ]
            }
        }
    },
    "sentences": [
        [
            "In",
            "case",
            "you",
            "missed",
            "this",
            "article",
            "from",
            "Sunday",
            "'s",
            "NY",
            "Times",
            ".",
            "Kal"
        ],
        [
            "Welcome",
            "back",
            "to",
            "work",
            ":",
            "-",
            ">",
            ")"
        ],
        [
            [
                ""
            ]
        ],
        [
            [
                ""
            ]
        ],
        [
            [
                ""
            ]
        ]
    ]
}