{
    "events": {
        "turn_0": {
            "Deliver_Data": {
                "labels": [
                    [
                        "Deliver_Data:B-Deliver members",
                        "Deliver_Data:I-Deliver Members",
                        "O",
                        "O",
                        "Deliver_Data:B-Data idString",
                        "Deliver_Data:I-Data idString",
                        "Deliver_Data:I-Data idString",
                        "Deliver_Data:I-Data idString",
                        "Deliver_Data:I-Data idString",
                        "Deliver_Data:I-Data idString",
                        "Deliver_Data:I-Data idString",
                        "Deliver_Data:I-Data idString",
                        "Deliver_Data:I-Data idString",
                        "Deliver_Data:I-Data idString",
                        "Deliver_Data:I-Data idString",
                        "Deliver_Data:I-Data idString",
                        "Deliver_Data:I-Data idString",
                        "Deliver_Data:I-Data idString",
                        "Deliver_Data:I-Data idString",
                        "Deliver_Data:I-Data idString",
                        "Deliver_Data:I-Data idString",
                        "O",
                        "O",
                        "O",
                        "O",
                        "O",
                        "O",
                        "O",
                        "O",
                        "O",
                        "O",
                        "O",
                        "O",
                        "O",
                        "O",
                        "O",
                        "O",
                        "O",
                        "O",
                        "O",
                        "O",
                        "O",
                        "O",
                        "O",
                        "O",
                        "O",
                        "O",
                        "O",
                        "O",
                        "O",
                        "O",
                        "O",
                        "O",
                        "O",
                        "O",
                        "O",
                        "O",
                        "O",
                        "O",
                        "O"
                    ],
                    [
                        "Deliver_Data:B-Deliver members",
                        "Deliver_Data:I-Deliver Members",
                        "O",
                        "O",
                        "O",
                        "O",
                        "O",
                        "O",
                        "O",
                        "O",
                        "O",
                        "O",
                        "O",
                        "O",
                        "O",
                        "O",
                        "O",
                        "O",
                        "O",
                        "O",
                        "O",
                        "O",
                        "O",
                        "Deliver_Data:B-Data idString",
                        "Deliver_Data:I-Data idString",
                        "Deliver_Data:I-Data idString",
                        "Deliver_Data:I-Data idString",
                        "Deliver_Data:I-Data idString",
                        "Deliver_Data:I-Data idString",
                        "Deliver_Data:I-Data idString",
                        "Deliver_Data:I-Data idString",
                        "O",
                        "O",
                        "O",
                        "O",
                        "O",
                        "O",
                        "O",
                        "O",
                        "O",
                        "O",
                        "O",
                        "O",
                        "O",
                        "O",
                        "O",
                        "O",
                        "O",
                        "O",
                        "O",
                        "O",
                        "O",
                        "O",
                        "O",
                        "O",
                        "O",
                        "O",
                        "O",
                        "O",
                        "O"
                    ]
                ],
                "triggers": [
                    "{'words': 'attached notice', 'indices': '3 4'}",
                    "{'words': 'attached new procedure', 'indices': '3 24 25'}"
                ],
                "extras": [
                    "Deliver Confirmation : ",
                    "Deliver Confirmation : "
                ]
            },
            "Request_Action": {
                "labels": [
                    [
                        "Request_Action:B-Action Members",
                        "Request_Action:I-Action Members",
                        "O",
                        "O",
                        "O",
                        "O",
                        "O",
                        "O",
                        "O",
                        "O",
                        "O",
                        "O",
                        "O",
                        "O",
                        "O",
                        "O",
                        "O",
                        "O",
                        "O",
                        "O",
                        "O",
                        "O",
                        "O",
                        "O",
                        "O",
                        "O",
                        "O",
                        "O",
                        "O",
                        "O",
                        "O",
                        "O",
                        "Request_Action:B-Action Description",
                        "Request_Action:I-Action Description",
                        "Request_Action:I-Action Description",
                        "Request_Action:I-Action Description",
                        "Request_Action:I-Action Description",
                        "Request_Action:I-Action Description",
                        "Request_Action:I-Action Description",
                        "Request_Action:I-Action Description",
                        "Request_Action:I-Action Description",
                        "Request_Action:I-Action Description",
                        "Request_Action:I-Action Description",
                        "Request_Action:I-Action Description",
                        "Request_Action:I-Action Description",
                        "Request_Action:I-Action Description",
                        "Request_Action:I-Action Description",
                        "Request_Action:I-Action Description",
                        "Request_Action:I-Action Description",
                        "Request_Action:I-Action Description",
                        "Request_Action:I-Action Description",
                        "Request_Action:I-Action Description",
                        "Request_Action:I-Action Description",
                        "O",
                        "O",
                        "O",
                        "O",
                        "O",
                        "O",
                        "O"
                    ]
                ],
                "triggers": [
                    "{'words': 'Please pass', 'indices': '32 33'}"
                ],
                "extras": [
                    ""
                ]
            }
        },
        "turn_1": {
            "Deliver_Action_Data": {
                "labels": [
                    [
                        "Deliver_Action_Data:B-Action Members",
                        "Deliver_Action_Data:B-Action Description",
                        "Deliver_Action_Data:I-Action Description",
                        "Deliver_Action_Data:I-Action Description",
                        "Deliver_Action_Data:I-Action Description",
                        "Deliver_Action_Data:I-Action Description",
                        "Deliver_Action_Data:I-Action Description",
                        "Deliver_Action_Data:I-Action Description",
                        "Deliver_Action_Data:I-Action Description",
                        "Deliver_Action_Data:I-Action Description",
                        "Deliver_Action_Data:I-Action Description",
                        "Deliver_Action_Data:I-Action Description",
                        "O",
                        "O",
                        "O",
                        "O",
                        "O",
                        "O",
                        "O",
                        "O",
                        "O",
                        "O",
                        "O",
                        "O",
                        "O",
                        "O",
                        "O",
                        "O",
                        "O",
                        "O",
                        "O",
                        "O",
                        "O",
                        "O",
                        "O",
                        "O",
                        "O",
                        "O",
                        "O",
                        "O",
                        "O",
                        "O",
                        "O",
                        "O",
                        "O",
                        "O",
                        "O",
                        "O",
                        "O",
                        "O",
                        "O",
                        "O",
                        "O",
                        "O",
                        "O",
                        "O",
                        "O",
                        "O",
                        "O",
                        "O",
                        "O",
                        "O",
                        "O",
                        "O",
                        "O",
                        "O",
                        "O",
                        "O",
                        "O",
                        "O",
                        "O",
                        "O",
                        "O",
                        "O",
                        "O",
                        "O",
                        "O",
                        "O",
                        "O",
                        "O",
                        "O",
                        "O",
                        "O",
                        "O",
                        "O",
                        "O",
                        "O",
                        "O",
                        "O",
                        "O",
                        "O",
                        "O",
                        "O",
                        "O",
                        "O",
                        "O",
                        "O",
                        "O",
                        "O",
                        "O",
                        "O",
                        "O",
                        "O",
                        "O",
                        "O",
                        "O",
                        "O",
                        "O",
                        "O",
                        "O",
                        "O",
                        "O",
                        "O",
                        "O",
                        "O",
                        "O",
                        "O",
                        "O",
                        "O",
                        "O",
                        "O",
                        "O",
                        "O",
                        "O",
                        "O",
                        "O",
                        "O",
                        "O",
                        "O",
                        "O",
                        "O",
                        "O",
                        "O",
                        "O",
                        "O",
                        "O",
                        "O",
                        "O",
                        "O",
                        "O",
                        "O",
                        "O",
                        "O",
                        "O",
                        "O",
                        "O",
                        "O",
                        "O",
                        "O",
                        "O",
                        "O",
                        "O"
                    ],
                    [
                        "O",
                        "O",
                        "O",
                        "O",
                        "O",
                        "O",
                        "O",
                        "O",
                        "O",
                        "O",
                        "O",
                        "O",
                        "O",
                        "O",
                        "O",
                        "O",
                        "O",
                        "O",
                        "O",
                        "O",
                        "O",
                        "O",
                        "O",
                        "O",
                        "O",
                        "O",
                        "O",
                        "O",
                        "O",
                        "O",
                        "O",
                        "O",
                        "O",
                        "O",
                        "O",
                        "Deliver_Action_Data:B-Action Time",
                        "Deliver_Action_Data:I-Action Time",
                        "Deliver_Action_Data:I-Action Time",
                        "O",
                        "Deliver_Action_Data:B-Action Date",
                        "Deliver_Action_Data:I-Action Date",
                        "Deliver_Action_Data:I-Action Date",
                        "Deliver_Action_Data:I-Action Date",
                        "O",
                        "Deliver_Action_Data:B-Action Members",
                        "Deliver_Action_Data:I-Action Members",
                        "Deliver_Action_Data:B-Action Description",
                        "Deliver_Action_Data:I-Action Description",
                        "Deliver_Action_Data:I-Action Description",
                        "Deliver_Action_Data:I-Action Description",
                        "Deliver_Action_Data:I-Action Description",
                        "Deliver_Action_Data:I-Action Description",
                        "Deliver_Action_Data:I-Action Description",
                        "Deliver_Action_Data:I-Action Description",
                        "Deliver_Action_Data:I-Action Description",
                        "Deliver_Action_Data:I-Action Description",
                        "O",
                        "O",
                        "O",
                        "O",
                        "O",
                        "O",
                        "O",
                        "O",
                        "O",
                        "O",
                        "O",
                        "O",
                        "O",
                        "O",
                        "O",
                        "O",
                        "O",
                        "O",
                        "O",
                        "O",
                        "O",
                        "O",
                        "O",
                        "O",
                        "O",
                        "O",
                        "O",
                        "O",
                        "O",
                        "O",
                        "O",
                        "O",
                        "O",
                        "O",
                        "O",
                        "O",
                        "O",
                        "O",
                        "O",
                        "O",
                        "O",
                        "O",
                        "O",
                        "O",
                        "O",
                        "O",
                        "O",
                        "O",
                        "O",
                        "O",
                        "O",
                        "O",
                        "O",
                        "O",
                        "O",
                        "O",
                        "O",
                        "O",
                        "O",
                        "O",
                        "O",
                        "O",
                        "O",
                        "O",
                        "O",
                        "O",
                        "O",
                        "O",
                        "O",
                        "O",
                        "O",
                        "O",
                        "O",
                        "O",
                        "O",
                        "O",
                        "O",
                        "O",
                        "O",
                        "O",
                        "O",
                        "O",
                        "O",
                        "O",
                        "O",
                        "O",
                        "O",
                        "O",
                        "O",
                        "O",
                        "O",
                        "O",
                        "O",
                        "O",
                        "O",
                        "O"
                    ],
                    [
                        "O",
                        "O",
                        "O",
                        "O",
                        "O",
                        "O",
                        "O",
                        "O",
                        "O",
                        "O",
                        "O",
                        "O",
                        "O",
                        "O",
                        "O",
                        "O",
                        "O",
                        "O",
                        "O",
                        "O",
                        "O",
                        "O",
                        "O",
                        "O",
                        "O",
                        "O",
                        "O",
                        "O",
                        "O",
                        "O",
                        "O",
                        "O",
                        "O",
                        "O",
                        "O",
                        "O",
                        "O",
                        "O",
                        "O",
                        "O",
                        "O",
                        "O",
                        "O",
                        "O",
                        "O",
                        "O",
                        "O",
                        "O",
                        "O",
                        "O",
                        "O",
                        "O",
                        "O",
                        "O",
                        "O",
                        "O",
                        "O",
                        "O",
                        "O",
                        "Deliver_Action_Data:B-Action Members",
                        "Deliver_Action_Data:I-Action Members",
                        "O",
                        "O",
                        "O",
                        "Deliver_Action_Data:B-Action Description",
                        "Deliver_Action_Data:I-Action Description",
                        "Deliver_Action_Data:I-Action Description",
                        "Deliver_Action_Data:I-Action Description",
                        "Deliver_Action_Data:I-Action Description",
                        "Deliver_Action_Data:I-Action Description",
                        "Deliver_Action_Data:I-Action Description",
                        "Deliver_Action_Data:I-Action Description",
                        "Deliver_Action_Data:I-Action Description",
                        "Deliver_Action_Data:I-Action Description",
                        "Deliver_Action_Data:I-Action Description",
                        "Deliver_Action_Data:I-Action Description",
                        "Deliver_Action_Data:I-Action Description",
                        "Deliver_Action_Data:I-Action Description",
                        "Deliver_Action_Data:B-Action Date",
                        "Deliver_Action_Data:I-Action Date",
                        "Deliver_Action_Data:I-Action Date",
                        "Deliver_Action_Data:I-Action Date",
                        "Deliver_Action_Data:I-Action Date",
                        "Deliver_Action_Data:I-Action Date",
                        "Deliver_Action_Data:I-Action Time",
                        "O",
                        "O",
                        "O",
                        "O",
                        "O",
                        "O",
                        "O",
                        "O",
                        "O",
                        "O",
                        "O",
                        "O",
                        "O",
                        "O",
                        "O",
                        "O",
                        "O",
                        "O",
                        "O",
                        "O",
                        "O",
                        "O",
                        "O",
                        "O",
                        "O",
                        "O",
                        "O",
                        "O",
                        "O",
                        "O",
                        "O",
                        "O",
                        "O",
                        "O",
                        "O",
                        "O",
                        "O",
                        "O",
                        "O",
                        "O",
                        "O",
                        "O",
                        "O",
                        "O",
                        "O",
                        "O",
                        "O",
                        "O",
                        "O",
                        "O",
                        "O",
                        "O",
                        "O",
                        "O",
                        "O",
                        "O",
                        "O",
                        "O",
                        "O",
                        "O",
                        "O",
                        "O",
                        "O",
                        "O",
                        "O",
                        "O",
                        "O"
                    ],
                    [
                        "O",
                        "O",
                        "O",
                        "O",
                        "O",
                        "O",
                        "O",
                        "O",
                        "O",
                        "O",
                        "O",
                        "O",
                        "O",
                        "O",
                        "O",
                        "O",
                        "O",
                        "O",
                        "O",
                        "O",
                        "O",
                        "O",
                        "O",
                        "O",
                        "O",
                        "O",
                        "O",
                        "O",
                        "O",
                        "O",
                        "O",
                        "O",
                        "O",
                        "O",
                        "O",
                        "O",
                        "O",
                        "O",
                        "O",
                        "O",
                        "O",
                        "O",
                        "O",
                        "O",
                        "O",
                        "O",
                        "O",
                        "O",
                        "O",
                        "O",
                        "O",
                        "O",
                        "O",
                        "O",
                        "O",
                        "O",
                        "O",
                        "O",
                        "O",
                        "Deliver_Action_Data:B-Action Description",
                        "Deliver_Action_Data:I-Action Description",
                        "O",
                        "O",
                        "O",
                        "O",
                        "O",
                        "O",
                        "O",
                        "O",
                        "O",
                        "O",
                        "O",
                        "O",
                        "O",
                        "O",
                        "O",
                        "O",
                        "O",
                        "O",
                        "O",
                        "O",
                        "O",
                        "O",
                        "O",
                        "O",
                        "O",
                        "O",
                        "O",
                        "O",
                        "O",
                        "Deliver_Action_Data:B-Action Description",
                        "Deliver_Action_Data:I-Action Description",
                        "Deliver_Action_Data:I-Action Description",
                        "Deliver_Action_Data:I-Action Description",
                        "Deliver_Action_Data:I-Action Description",
                        "Deliver_Action_Data:I-Action Description",
                        "Deliver_Action_Data:B-Action Date",
                        "Deliver_Action_Data:I-Action Date",
                        "Deliver_Action_Data:I-Action Date",
                        "Deliver_Action_Data:I-Action Date",
                        "Deliver_Action_Data:I-Action Date",
                        "O",
                        "O",
                        "O",
                        "O",
                        "O",
                        "O",
                        "O",
                        "O",
                        "O",
                        "O",
                        "O",
                        "O",
                        "O",
                        "O",
                        "O",
                        "O",
                        "O",
                        "O",
                        "O",
                        "O",
                        "O",
                        "O",
                        "O",
                        "O",
                        "O",
                        "O",
                        "O",
                        "O",
                        "O",
                        "O",
                        "O",
                        "O",
                        "O",
                        "O",
                        "O",
                        "O",
                        "O",
                        "O",
                        "O",
                        "O",
                        "O",
                        "O",
                        "O",
                        "O",
                        "O",
                        "O",
                        "O",
                        "O",
                        "O",
                        "O",
                        "O"
                    ]
                ],
                "triggers": [
                    "{'words': 'suspending', 'indices': '3'}",
                    "{'words': 'will alter', 'indices': '46 47'}",
                    "{'words': 'will continue', 'indices': '64 65'}",
                    "{'words': 'now ensure', 'indices': '89 90'}"
                ],
                "extras": [
                    "Deliver Confirmation : ",
                    "Deliver Confirmation : ",
                    "Deliver Confirmation : ",
                    "Deliver Confirmation : "
                ]
            },
            "Request_Action": {
                "labels": [
                    [
                        "O",
                        "O",
                        "O",
                        "O",
                        "O",
                        "O",
                        "O",
                        "O",
                        "O",
                        "O",
                        "O",
                        "O",
                        "O",
                        "O",
                        "O",
                        "O",
                        "O",
                        "O",
                        "O",
                        "O",
                        "O",
                        "O",
                        "O",
                        "O",
                        "O",
                        "O",
                        "O",
                        "O",
                        "O",
                        "O",
                        "O",
                        "O",
                        "O",
                        "O",
                        "O",
                        "O",
                        "O",
                        "O",
                        "O",
                        "O",
                        "O",
                        "O",
                        "O",
                        "O",
                        "O",
                        "O",
                        "O",
                        "O",
                        "O",
                        "O",
                        "O",
                        "O",
                        "O",
                        "O",
                        "O",
                        "O",
                        "O",
                        "O",
                        "O",
                        "O",
                        "O",
                        "O",
                        "O",
                        "O",
                        "O",
                        "O",
                        "O",
                        "O",
                        "O",
                        "O",
                        "O",
                        "O",
                        "O",
                        "O",
                        "O",
                        "O",
                        "O",
                        "O",
                        "O",
                        "O",
                        "O",
                        "O",
                        "O",
                        "O",
                        "O",
                        "O",
                        "O",
                        "O",
                        "O",
                        "O",
                        "O",
                        "O",
                        "O",
                        "O",
                        "O",
                        "O",
                        "O",
                        "O",
                        "O",
                        "O",
                        "O",
                        "O",
                        "O",
                        "O",
                        "O",
                        "O",
                        "O",
                        "O",
                        "O",
                        "O",
                        "O",
                        "O",
                        "O",
                        "O",
                        "O",
                        "O",
                        "O",
                        "O",
                        "O",
                        "O",
                        "O",
                        "O",
                        "O",
                        "O",
                        "O",
                        "O",
                        "O",
                        "Request_Action:B-Action Members",
                        "Request_Action:I-Action Members",
                        "Request_Action:B-Action Description",
                        "Request_Action:I-Action Description",
                        "Request_Action:I-Action Description",
                        "Request_Action:I-Action Description",
                        "Request_Action:I-Action Description",
                        "Request_Action:I-Action Description",
                        "Request_Action:I-Action Description",
                        "Request_Action:I-Action Description",
                        "Request_Action:I-Action Description",
                        "Request_Action:I-Action Description",
                        "Request_Action:I-Action Description",
                        "O",
                        "O",
                        "O",
                        "O",
                        "O",
                        "O",
                        "O",
                        "O",
                        "O",
                        "O",
                        "O",
                        "O"
                    ]
                ],
                "triggers": [
                    "{'words': 'must continue', 'indices': '129 130'}"
                ],
                "extras": [
                    ""
                ]
            }
        }
    },
    "sentences": [
        [
            "Market",
            "Participants",
            "The",
            "attached",
            "notice",
            "describes",
            "changes",
            "going",
            "into",
            "effect",
            "at",
            "23:59",
            "tonight",
            "regarding",
            "discontinuance",
            "of",
            "non-public",
            "information",
            "flow",
            "to",
            "CDWR",
            "and",
            "also",
            "a",
            "new",
            "procedure",
            "for",
            "payment",
            "of",
            "Intertie",
            "bids",
            ".",
            "Please",
            "pass",
            "this",
            "message",
            "immediately",
            "to",
            "all",
            "departments",
            "that",
            "could",
            "be",
            "involved",
            "in",
            "real-time",
            "bids",
            "and",
            "dispatches",
            "in",
            "the",
            "California",
            "markets",
            ".",
            "Client",
            "Relations",
            "Communications",
            "CRCommunications",
            "@",
            "caiso.com"
        ],
        [
            "CAISO",
            "is",
            "essentially",
            "suspending",
            "10-minute",
            "dispatch",
            "for",
            "energy",
            "supplied",
            "on",
            "the",
            "ties",
            "!",
            "If",
            "you",
            "get",
            "dispatched",
            "at",
            "the",
            "beginning",
            "of",
            "the",
            "hour",
            ",",
            "you",
            "will",
            "stay",
            "on",
            "for",
            "the",
            "entire",
            "hour",
            ".",
            "Alan",
            "Comnes",
            "Beginning",
            "at",
            "2359",
            "on",
            "December",
            "12",
            ",",
            "2001",
            ",",
            "the",
            "ISO",
            "will",
            "alter",
            "the",
            "way",
            "it",
            "pays",
            "inter-tie",
            "bids",
            "for",
            "Energy",
            ".",
            "Specifically",
            ",",
            "the",
            "ISO",
            "(",
            "1",
            ")",
            "will",
            "continue",
            "to",
            "pre-dispatch",
            "an",
            "inter-tie",
            "bid",
            "in",
            "merit",
            "order",
            "in",
            "the",
            "BEEP",
            "stack",
            "before",
            "the",
            "beginning",
            "of",
            "the",
            "operating",
            "hour",
            "but",
            "(",
            "2",
            ")",
            "now",
            "ensure",
            "such",
            "a",
            "bid",
            "is",
            "dispatched",
            "throughout",
            "the",
            "entire",
            "operating",
            "hour",
            "(",
            "i.e.",
            ",",
            "never",
            "reversed",
            ")",
            ",",
            "thus",
            "paying",
            "the",
            "bid",
            "the",
            "Instructed",
            "Energy",
            "Price",
            "for",
            "all",
            "ten-minute",
            "intervals",
            "in",
            "that",
            "hour",
            ".",
            "As",
            "before",
            ",",
            "the",
            "ISO",
            "must",
            "continue",
            "to",
            "comply",
            "with",
            "the",
            "Commission",
            "'s",
            "June",
            "19",
            "Order",
            "and",
            "so",
            "the",
            "inter-ties",
            "can",
            "not",
            "set",
            "the",
            "Market",
            "Clearing",
            "Price",
            "."
        ]
    ]
}