{
    "events": {
        "turn_0": {
            "Deliver_Data": {
                "labels": [
                    [
                        "Deliver_Data:B-Deliver members",
                        "Deliver_Data:B-Data Value",
                        "Deliver_Data:I-Data Value",
                        "O",
                        "O",
                        "Deliver_Data:B-Data idString",
                        "Deliver_Data:I-Data idString",
                        "Deliver_Data:I-Data idString",
                        "Deliver_Data:I-Data idString",
                        "Deliver_Data:I-Data idString",
                        "Deliver_Data:I-Data idString",
                        "Deliver_Data:I-Data idString",
                        "Deliver_Data:I-Data idString",
                        "Deliver_Data:I-Data idString",
                        "Deliver_Data:I-Data idString",
                        "Deliver_Data:I-Data idString",
                        "Deliver_Data:I-Data idString",
                        "Deliver_Data:I-Data idString",
                        "O",
                        "O",
                        "O",
                        "O",
                        "O",
                        "O",
                        "O",
                        "O",
                        "O",
                        "O",
                        "O",
                        "O",
                        "O",
                        "O",
                        "O",
                        "O",
                        "O",
                        "O",
                        "O",
                        "O",
                        "O",
                        "O",
                        "O",
                        "O",
                        "O",
                        "O",
                        "O",
                        "O",
                        "O",
                        "O",
                        "O",
                        "O",
                        "O",
                        "O",
                        "O",
                        "O",
                        "O",
                        "O",
                        "O",
                        "O",
                        "O",
                        "O",
                        "O",
                        "O",
                        "O",
                        "O",
                        "O",
                        "O",
                        "O",
                        "O",
                        "O",
                        "O",
                        "O",
                        "O",
                        "O",
                        "O",
                        "O",
                        "O",
                        "O",
                        "O",
                        "O",
                        "O",
                        "O",
                        "O",
                        "O",
                        "O",
                        "O",
                        "O",
                        "O",
                        "O",
                        "O"
                    ]
                ],
                "triggers": [
                    "{'words': 'is a', 'indices': '3 4'}"
                ],
                "extras": [
                    "Deliver Confirmation : "
                ]
            },
            "Deliver_Action_Data": {
                "labels": [
                    [
                        "O",
                        "O",
                        "O",
                        "O",
                        "O",
                        "O",
                        "O",
                        "O",
                        "O",
                        "O",
                        "O",
                        "O",
                        "O",
                        "O",
                        "O",
                        "O",
                        "O",
                        "O",
                        "O",
                        "O",
                        "O",
                        "O",
                        "O",
                        "O",
                        "O",
                        "O",
                        "O",
                        "O",
                        "O",
                        "O",
                        "O",
                        "O",
                        "O",
                        "O",
                        "O",
                        "O",
                        "O",
                        "O",
                        "O",
                        "O",
                        "O",
                        "O",
                        "O",
                        "O",
                        "O",
                        "Deliver_Action_Data:B-Action Members",
                        "Deliver_Action_Data:B-Action Description",
                        "Deliver_Action_Data:I-Action Description",
                        "Deliver_Action_Data:I-Action Description",
                        "Deliver_Action_Data:I-Action Description",
                        "Deliver_Action_Data:I-Action Description",
                        "Deliver_Action_Data:I-Action Description",
                        "Deliver_Action_Data:I-Action Description",
                        "Deliver_Action_Data:I-Action Description",
                        "Deliver_Action_Data:I-Action Description",
                        "Deliver_Action_Data:I-Action Description",
                        "Deliver_Action_Data:I-Action Description",
                        "Deliver_Action_Data:I-Action Description",
                        "Deliver_Action_Data:I-Action Description",
                        "Deliver_Action_Data:I-Action Description",
                        "Deliver_Action_Data:I-Action Description",
                        "Deliver_Action_Data:I-Action Description",
                        "Deliver_Action_Data:I-Action Description",
                        "Deliver_Action_Data:I-Action Description",
                        "Deliver_Action_Data:I-Action Description",
                        "Deliver_Action_Data:I-Action Description",
                        "Deliver_Action_Data:I-Action Description",
                        "Deliver_Action_Data:I-Action Description",
                        "Deliver_Action_Data:I-Action Description",
                        "Deliver_Action_Data:I-Action Description",
                        "Deliver_Action_Data:I-Action Description",
                        "Deliver_Action_Data:I-Action Description",
                        "Deliver_Action_Data:I-Action Description",
                        "Deliver_Action_Data:I-Action Description",
                        "Deliver_Action_Data:I-Action Description",
                        "Deliver_Action_Data:I-Action Description",
                        "Deliver_Action_Data:I-Action Description",
                        "Deliver_Action_Data:I-Action Description",
                        "Deliver_Action_Data:I-Action Description",
                        "Deliver_Action_Data:I-Action Description",
                        "Deliver_Action_Data:I-Action Description",
                        "Deliver_Action_Data:I-Action Description",
                        "Deliver_Action_Data:I-Action Description",
                        "Deliver_Action_Data:I-Action Description",
                        "Deliver_Action_Data:I-Action Description",
                        "Deliver_Action_Data:I-Action Description",
                        "Deliver_Action_Data:I-Action Description",
                        "Deliver_Action_Data:I-Action Description",
                        "Deliver_Action_Data:I-Action Description"
                    ]
                ],
                "triggers": [
                    "{'words': 'to include', 'indices': '46 47'}"
                ],
                "extras": [
                    "Deliver Confirmation : "
                ]
            }
        },
        "turn_1": {
            "Deliver_Data": {
                "labels": [
                    [
                        "Deliver_Data:B-Deliver members",
                        "Deliver_Data:B-Data Value",
                        "O",
                        "Deliver_Data:B-Data idString",
                        "Deliver_Data:I-Data idString",
                        "Deliver_Data:I-Data idString",
                        "Deliver_Data:I-Data idString",
                        "Deliver_Data:I-Data idString",
                        "Deliver_Data:I-Data idString",
                        "O",
                        "O",
                        "O",
                        "O",
                        "O",
                        "O",
                        "O",
                        "O",
                        "O",
                        "O",
                        "O",
                        "O",
                        "O",
                        "O",
                        "O",
                        "O",
                        "O",
                        "O",
                        "O",
                        "O",
                        "O",
                        "O",
                        "O",
                        "O",
                        "O",
                        "O",
                        "O",
                        "O",
                        "O",
                        "O",
                        "O",
                        "O",
                        "O",
                        "O",
                        "O",
                        "O",
                        "O",
                        "O",
                        "O",
                        "O",
                        "O",
                        "O",
                        "O",
                        "O",
                        "O",
                        "O",
                        "O",
                        "O",
                        "O",
                        "O",
                        "O",
                        "O",
                        "O",
                        "O",
                        "O",
                        "O",
                        "O",
                        "O",
                        "O",
                        "O",
                        "O",
                        "O",
                        "O",
                        "O",
                        "O",
                        "O",
                        "O",
                        "O",
                        "O",
                        "O",
                        "O",
                        "O",
                        "O",
                        "O",
                        "O",
                        "O",
                        "O",
                        "O",
                        "O",
                        "O",
                        "O",
                        "O",
                        "O",
                        "O",
                        "O",
                        "O",
                        "O",
                        "O",
                        "O",
                        "O",
                        "O",
                        "O",
                        "O",
                        "O",
                        "O",
                        "O",
                        "O",
                        "O",
                        "O",
                        "O",
                        "O",
                        "O",
                        "O",
                        "O",
                        "O",
                        "O",
                        "O",
                        "O",
                        "O",
                        "O",
                        "O",
                        "O",
                        "O"
                    ]
                ],
                "triggers": [
                    "{'words': 'is the', 'indices': '2 3'}"
                ],
                "extras": [
                    "Deliver Confirmation : "
                ]
            },
            "Deliver_Action_Data": {
                "labels": [
                    [
                        "O",
                        "O",
                        "O",
                        "O",
                        "O",
                        "O",
                        "O",
                        "O",
                        "O",
                        "O",
                        "O",
                        "O",
                        "O",
                        "O",
                        "O",
                        "O",
                        "O",
                        "O",
                        "O",
                        "O",
                        "O",
                        "O",
                        "Deliver_Action_Data:B-Action Members",
                        "Deliver_Action_Data:B-Action Description",
                        "Deliver_Action_Data:I-Action Description",
                        "Deliver_Action_Data:I-Action Description",
                        "Deliver_Action_Data:I-Action Description",
                        "Deliver_Action_Data:I-Action Description",
                        "Deliver_Action_Data:I-Action Description",
                        "Deliver_Action_Data:B-Action Date",
                        "Deliver_Action_Data:I-Action Date",
                        "Deliver_Action_Data:I-Action Date",
                        "Deliver_Action_Data:I-Action Date",
                        "O",
                        "O",
                        "O",
                        "O",
                        "O",
                        "O",
                        "O",
                        "O",
                        "O",
                        "O",
                        "O",
                        "O",
                        "O",
                        "O",
                        "O",
                        "O",
                        "O",
                        "O",
                        "O",
                        "O",
                        "O",
                        "O",
                        "O",
                        "O",
                        "O",
                        "O",
                        "O",
                        "O",
                        "O",
                        "O",
                        "O",
                        "O",
                        "O",
                        "O",
                        "O",
                        "O",
                        "O",
                        "O",
                        "O",
                        "O",
                        "O",
                        "O",
                        "O",
                        "O",
                        "O",
                        "O",
                        "O",
                        "O",
                        "O",
                        "O",
                        "O",
                        "O",
                        "O",
                        "O",
                        "O",
                        "O",
                        "O",
                        "O",
                        "O",
                        "O",
                        "O",
                        "O",
                        "O",
                        "O",
                        "O",
                        "O",
                        "O",
                        "O",
                        "O",
                        "O",
                        "O",
                        "O",
                        "O",
                        "O",
                        "O",
                        "O",
                        "O",
                        "O",
                        "O",
                        "O",
                        "O",
                        "O",
                        "O",
                        "O",
                        "O",
                        "O",
                        "O",
                        "O",
                        "O"
                    ],
                    [
                        "O",
                        "O",
                        "O",
                        "O",
                        "O",
                        "O",
                        "O",
                        "O",
                        "O",
                        "O",
                        "O",
                        "O",
                        "O",
                        "O",
                        "O",
                        "O",
                        "O",
                        "O",
                        "O",
                        "O",
                        "O",
                        "O",
                        "O",
                        "O",
                        "O",
                        "O",
                        "O",
                        "O",
                        "O",
                        "O",
                        "O",
                        "O",
                        "O",
                        "O",
                        "Deliver_Action_Data:B-Action Members",
                        "Deliver_Action_Data:I-Action Members",
                        "Deliver_Action_Data:B-Action Description",
                        "Deliver_Action_Data:I-Action Description",
                        "Deliver_Action_Data:I-Action Description",
                        "Deliver_Action_Data:B-Action Time",
                        "Deliver_Action_Data:I-Action Time",
                        "O",
                        "O",
                        "O",
                        "O",
                        "O",
                        "O",
                        "O",
                        "O",
                        "O",
                        "O",
                        "O",
                        "O",
                        "O",
                        "O",
                        "O",
                        "O",
                        "O",
                        "O",
                        "O",
                        "O",
                        "O",
                        "O",
                        "O",
                        "O",
                        "O",
                        "O",
                        "O",
                        "O",
                        "O",
                        "O",
                        "O",
                        "O",
                        "O",
                        "O",
                        "O",
                        "O",
                        "O",
                        "O",
                        "O",
                        "O",
                        "O",
                        "O",
                        "O",
                        "O",
                        "O",
                        "O",
                        "O",
                        "O",
                        "O",
                        "O",
                        "O",
                        "O",
                        "O",
                        "O",
                        "O",
                        "O",
                        "O",
                        "O",
                        "O",
                        "O",
                        "O",
                        "O",
                        "O",
                        "O",
                        "O",
                        "O",
                        "O",
                        "O",
                        "O",
                        "O",
                        "O",
                        "O",
                        "O",
                        "O",
                        "O",
                        "O",
                        "O",
                        "O",
                        "O",
                        "O",
                        "O"
                    ],
                    [
                        "O",
                        "O",
                        "O",
                        "O",
                        "O",
                        "O",
                        "O",
                        "O",
                        "O",
                        "O",
                        "O",
                        "O",
                        "O",
                        "O",
                        "O",
                        "O",
                        "O",
                        "O",
                        "O",
                        "O",
                        "O",
                        "O",
                        "O",
                        "O",
                        "O",
                        "O",
                        "O",
                        "O",
                        "O",
                        "O",
                        "O",
                        "O",
                        "O",
                        "O",
                        "O",
                        "O",
                        "O",
                        "O",
                        "O",
                        "O",
                        "O",
                        "O",
                        "Deliver_Action_Data:B-Action Members",
                        "Deliver_Action_Data:B-Action Description",
                        "Deliver_Action_Data:I-Action Description",
                        "Deliver_Action_Data:I-Action Description",
                        "Deliver_Action_Data:I-Action Description",
                        "Deliver_Action_Data:I-Action Description",
                        "Deliver_Action_Data:I-Action Description",
                        "Deliver_Action_Data:I-Action Description",
                        "Deliver_Action_Data:I-Action Description",
                        "Deliver_Action_Data:I-Action Description",
                        "Deliver_Action_Data:I-Action Description",
                        "Deliver_Action_Data:I-Action Description",
                        "Deliver_Action_Data:I-Action Description",
                        "O",
                        "O",
                        "O",
                        "O",
                        "O",
                        "O",
                        "O",
                        "O",
                        "O",
                        "O",
                        "O",
                        "O",
                        "O",
                        "O",
                        "O",
                        "O",
                        "O",
                        "O",
                        "O",
                        "O",
                        "O",
                        "O",
                        "O",
                        "O",
                        "O",
                        "O",
                        "O",
                        "O",
                        "O",
                        "O",
                        "O",
                        "O",
                        "O",
                        "O",
                        "O",
                        "O",
                        "O",
                        "O",
                        "O",
                        "O",
                        "O",
                        "O",
                        "O",
                        "O",
                        "O",
                        "O",
                        "O",
                        "O",
                        "O",
                        "O",
                        "O",
                        "O",
                        "O",
                        "O",
                        "O",
                        "O",
                        "O",
                        "O",
                        "O",
                        "O",
                        "O",
                        "O",
                        "O",
                        "O",
                        "O",
                        "O",
                        "O"
                    ]
                ],
                "triggers": [
                    "{'words': 'will e-mail', 'indices': '23 24'}",
                    "{'words': 'will be here', 'indices': '36 37 38'}",
                    "{'words': 'will give', 'indices': '43 44'}"
                ],
                "extras": [
                    "Deliver Confirmation : ",
                    "Deliver Confirmation : ",
                    "Deliver Confirmation : "
                ]
            }
        },
        "turn_2": {
            "Deliver_Action_Data": {
                "labels": [
                    [
                        "O",
                        "O",
                        "O",
                        "O",
                        "O",
                        "O",
                        "O",
                        "O",
                        "O",
                        "O",
                        "O",
                        "O",
                        "O",
                        "Deliver_Action_Data:B-Action Members",
                        "Deliver_Action_Data:B-Action Description",
                        "Deliver_Action_Data:I-Action Description",
                        "Deliver_Action_Data:I-Action Description",
                        "Deliver_Action_Data:I-Action Description",
                        "Deliver_Action_Data:I-Action Description",
                        "O",
                        "O",
                        "O",
                        "O",
                        "O",
                        "O",
                        "O",
                        "O",
                        "O",
                        "O",
                        "O",
                        "O",
                        "O",
                        "O",
                        "O",
                        "O",
                        "O"
                    ]
                ],
                "triggers": [
                    "{'words': 'sending', 'indices': '15'}"
                ],
                "extras": [
                    "Deliver Confirmation : "
                ]
            },
            "Request_Action": {
                "labels": [
                    [
                        "Request_Action:B-Action Members",
                        "O",
                        "O",
                        "O",
                        "O",
                        "O",
                        "O",
                        "O",
                        "O",
                        "O",
                        "O",
                        "O",
                        "O",
                        "O",
                        "O",
                        "O",
                        "O",
                        "O",
                        "O",
                        "O",
                        "O",
                        "O",
                        "O",
                        "Request_Action:B-Action Description",
                        "Request_Action:I-Action Description",
                        "Request_Action:I-Action Description",
                        "Request_Action:I-Action Description",
                        "Request_Action:I-Action Description",
                        "Request_Action:I-Action Description",
                        "Request_Action:I-Action Description",
                        "Request_Action:I-Action Description",
                        "O",
                        "O",
                        "O",
                        "O",
                        "O"
                    ]
                ],
                "triggers": [
                    "{'words': 'Please select', 'indices': '22 23'}"
                ],
                "extras": [
                    ""
                ]
            }
        }
    },
    "sentences": [
        [
            "Mansoor",
            "The",
            "I/C",
            "is",
            "a",
            "10",
            "''",
            "UltraSonic",
            "designed",
            "for",
            "a",
            "range",
            "of",
            "35",
            "mmcfd",
            "to",
            "+100",
            "mmcfd",
            ".",
            "By",
            "using",
            "the",
            "US",
            "meter",
            ",",
            "this",
            "allows",
            "a",
            "wide",
            "range",
            "of",
            "volumes",
            "without",
            "changing",
            "out",
            "the",
            "tube",
            "when",
            "Agave",
            "want",
            "to",
            "increase",
            "the",
            "volumes",
            ".",
            "I/C",
            "to",
            "include",
            "US",
            "meter",
            "H2S",
            "H2O",
            "Chromatograph",
            "Flow",
            "control",
            "Positive",
            "Shut",
            "in",
            "EFM",
            "DAS",
            "UPS",
            "Building",
            "GFC",
            "Material",
            "cost",
            "=",
            "Install",
            "cost",
            "(",
            "contractor",
            ",",
            "inspection",
            ",",
            "Dlab",
            ",",
            "Eng",
            ",",
            "Proj",
            ".",
            "man",
            ")",
            "=",
            "Contingency",
            "=",
            "OH",
            ",",
            "AFUDC",
            ",",
            "="
        ],
        [
            "David",
            "This",
            "is",
            "the",
            "equipment",
            "for",
            "the",
            "proposed",
            "interconnect",
            ".",
            "The",
            "Enron",
            "``",
            "e",
            "''",
            "nternet",
            "is",
            "down",
            "at",
            "this",
            "time",
            "and",
            "I",
            "will",
            "e-mail",
            "your",
            "the",
            "Engineering",
            "Standards",
            "when",
            "it",
            "is",
            "running",
            ".",
            "Jim",
            "Williams",
            "will",
            "be",
            "here",
            "this",
            "PM",
            "and",
            "I",
            "will",
            "give",
            "him",
            "a",
            "typical",
            "I/C",
            "package",
            "drawing",
            "and",
            "Material",
            "list",
            "set",
            "that",
            "you",
            "can",
            "review",
            ".",
            "This",
            "is",
            "a",
            "typical",
            "set",
            "and",
            "for",
            "your",
            "proposed",
            "I/C",
            ",",
            "a",
            "few",
            "modifications",
            "to",
            "package",
            "would",
            "be",
            "required",
            "but",
            "it",
            "is",
            "80",
            "%",
            "of",
            "what",
            "is",
            "used",
            "at",
            "most",
            "I/C",
            ".",
            "You",
            "can",
            "develop",
            "a",
            "cost",
            "estimate",
            "from",
            "this",
            "package",
            "with",
            "your",
            "modifications",
            ".",
            "If",
            "any",
            "questions",
            "or",
            "if",
            "I",
            "can",
            "be",
            "of",
            "assistance",
            ",",
            "please",
            "contact",
            "me",
            ".",
            "Earl",
            "Chanley"
        ],
        [
            "Earl",
            "We",
            "have",
            "a",
            "set",
            "of",
            "Engineering",
            "Standards",
            "in",
            "Planning",
            "common",
            "drive",
            "and",
            "Eric",
            "is",
            "sending",
            "them",
            "to",
            "you",
            "right",
            "now",
            ".",
            "Please",
            "select",
            "whatever",
            "you",
            "need",
            "to",
            "send",
            "to",
            "Agave",
            "ASAP",
            ".",
            "Regards",
            ",",
            "Mansoor"
        ]
    ]
}