{
    "events": {
        "turn_0": {
            "Deliver_Data": {
                "labels": [
                    [
                        "Deliver_Data:B-Data idString",
                        "Deliver_Data:I-Data idString",
                        "Deliver_Data:I-Data idString",
                        "Deliver_Data:I-Data idString",
                        "Deliver_Data:I-Data idString",
                        "Deliver_Data:I-Data idString",
                        "Deliver_Data:I-Data idString",
                        "O",
                        "Deliver_Data:B-Data Value",
                        "Deliver_Data:I-Data Value",
                        "Deliver_Data:I-Data Value",
                        "Deliver_Data:I-Data Value",
                        "Deliver_Data:I-Data Value",
                        "Deliver_Data:I-Data Value",
                        "O",
                        "O",
                        "O",
                        "O",
                        "O",
                        "O",
                        "O",
                        "O",
                        "O",
                        "O",
                        "O",
                        "O",
                        "O",
                        "O"
                    ]
                ],
                "triggers": [
                    "{'words': 'Progress Status', 'indices': '0 1'}"
                ],
                "extras": [
                    "Deliver Confirmation : "
                ]
            }
        },
        "turn_1": {
            "Deliver_Data": {
                "labels": [
                    [
                        "Deliver_Data:B-Data idString",
                        "Deliver_Data:I-Data idString",
                        "Deliver_Data:I-Data idString",
                        "Deliver_Data:I-Data idString",
                        "Deliver_Data:I-Data idString",
                        "Deliver_Data:I-Data idString",
                        "Deliver_Data:I-Data idString",
                        "O",
                        "Deliver_Data:B-Data Value",
                        "Deliver_Data:I-Data Value",
                        "Deliver_Data:I-Data Value",
                        "Deliver_Data:I-Data Value",
                        "Deliver_Data:I-Data Value",
                        "Deliver_Data:I-Data Value",
                        "Deliver_Data:I-Data Value",
                        "Deliver_Data:I-Data Value",
                        "Deliver_Data:I-Data Value",
                        "Deliver_Data:I-Data Value",
                        "Deliver_Data:I-Data Value",
                        "Deliver_Data:I-Data Value"
                    ]
                ],
                "triggers": [
                    "{'words': 'Progress Status', 'indices': '0 1'}"
                ],
                "extras": [
                    "Deliver Confirmation : "
                ]
            }
        },
        "turn_2": {
            "Deliver_Data": {
                "labels": [
                    [
                        "Deliver_Data:B-Data idString",
                        "Deliver_Data:I-Data idString",
                        "Deliver_Data:I-Data idString",
                        "Deliver_Data:I-Data idString",
                        "Deliver_Data:I-Data idString",
                        "Deliver_Data:I-Data idString",
                        "Deliver_Data:I-Data idString",
                        "O",
                        "Deliver_Data:B-Data Value",
                        "Deliver_Data:I-Data Value",
                        "Deliver_Data:I-Data Value",
                        "Deliver_Data:I-Data Value",
                        "Deliver_Data:I-Data Value",
                        "Deliver_Data:I-Data Value",
                        "Deliver_Data:I-Data Value",
                        "Deliver_Data:I-Data Value",
                        "Deliver_Data:I-Data Value",
                        "Deliver_Data:I-Data Value",
                        "Deliver_Data:I-Data Value",
                        "Deliver_Data:I-Data Value",
                        "O",
                        "O",
                        "O",
                        "O",
                        "O",
                        "O",
                        "O",
                        "O",
                        "O",
                        "O",
                        "O",
                        "O",
                        "O",
                        "O",
                        "O",
                        "O",
                        "O",
                        "O",
                        "O",
                        "O",
                        "O",
                        "O",
                        "O",
                        "O"
                    ]
                ],
                "triggers": [
                    "{'words': 'Progress Status', 'indices': '0 1'}"
                ],
                "extras": [
                    "Deliver Confirmation : "
                ]
            }
        },
        "turn_3": {
            "O": {
                "labels": [
                    [
                        "O"
                    ]
                ],
                "triggers": [
                    ""
                ],
                "extras": [
                    ""
                ]
            }
        }
    },
    "sentences": [
        [
            "Progress",
            "Status",
            "(",
            "so",
            "far",
            "...",
            ")",
            ":",
            "113",
            "converted",
            "out",
            "of",
            "701",
            "excels",
            "...",
            "Good",
            "Work",
            "...",
            "(",
            "Keep",
            "it",
            "up",
            "!",
            ")",
            "Thanks",
            ",",
            "Hal",
            "x53707"
        ],
        [
            "Progress",
            "Status",
            "(",
            "so",
            "far",
            "...",
            ")",
            ":",
            "235",
            "converted",
            "out",
            "of",
            "701",
            "excels",
            "...",
            "(",
            "33.5",
            "%",
            "done",
            ")"
        ],
        [
            "Progress",
            "Status",
            "(",
            "so",
            "far",
            "...",
            ")",
            ":",
            "352",
            "converted",
            "out",
            "of",
            "701",
            "excels",
            "...",
            "(",
            "50.2",
            "%",
            "done",
            ")",
            "I",
            "realize",
            "that",
            "not",
            "everyone",
            "is",
            "able",
            "to",
            "help",
            "the",
            "same",
            "amount",
            ",",
            "but",
            "it",
            "really",
            "helps",
            "whatever",
            "you",
            "can",
            "do",
            ".",
            "Thanks",
            "."
        ],
        [
            "FYI"
        ]
    ]
}