{
    "events": {
        "turn_0": {
            "Request_Action": {
                "labels": [
                    [
                        "Request_Action:B-Action Members",
                        "Request_Action:I-Action Members",
                        "O",
                        "O",
                        "Request_Action:B-Action Description",
                        "Request_Action:I-Action Description",
                        "Request_Action:I-Action Description",
                        "Request_Action:I-Action Description",
                        "Request_Action:I-Action Description",
                        "Request_Action:I-Action Description",
                        "Request_Action:I-Action Description",
                        "Request_Action:I-Action Description",
                        "Request_Action:I-Action Description",
                        "Request_Action:I-Action Description",
                        "Request_Action:I-Action Description",
                        "Request_Action:I-Action Description",
                        "Request_Action:I-Action Description",
                        "Request_Action:I-Action Description",
                        "Request_Action:I-Action Description",
                        "Request_Action:I-Action Description",
                        "Request_Action:I-Action Description",
                        "Request_Action:I-Action Description",
                        "Request_Action:I-Action Description",
                        "Request_Action:I-Action Description",
                        "Request_Action:I-Action Description",
                        "Request_Action:I-Action Description",
                        "Request_Action:I-Action Description",
                        "Request_Action:I-Action Description",
                        "Request_Action:I-Action Description",
                        "O",
                        "O",
                        "O",
                        "O",
                        "O",
                        "O",
                        "O",
                        "O",
                        "O",
                        "O",
                        "O",
                        "O",
                        "O",
                        "O",
                        "O",
                        "O",
                        "O",
                        "O",
                        "O",
                        "O",
                        "O",
                        "O",
                        "O",
                        "O",
                        "O",
                        "O",
                        "O",
                        "O",
                        "O",
                        "O",
                        "O",
                        "O",
                        "O",
                        "O",
                        "O",
                        "O",
                        "O",
                        "O",
                        "O",
                        "O",
                        "O",
                        "O"
                    ],
                    [
                        "Request_Action:B-Action Members",
                        "Request_Action:I-Action Members",
                        "O",
                        "O",
                        "O",
                        "O",
                        "O",
                        "O",
                        "O",
                        "O",
                        "O",
                        "O",
                        "O",
                        "O",
                        "O",
                        "O",
                        "O",
                        "O",
                        "O",
                        "O",
                        "O",
                        "O",
                        "O",
                        "O",
                        "O",
                        "O",
                        "O",
                        "O",
                        "O",
                        "O",
                        "Request_Action:B-Action Description",
                        "Request_Action:I-Action Description",
                        "Request_Action:I-Action Description",
                        "Request_Action:I-Action Description",
                        "Request_Action:I-Action Description",
                        "Request_Action:I-Action Description",
                        "Request_Action:I-Action Description",
                        "Request_Action:I-Action Description",
                        "Request_Action:I-Action Description",
                        "O",
                        "O",
                        "O",
                        "O",
                        "O",
                        "O",
                        "O",
                        "O",
                        "O",
                        "O",
                        "O",
                        "O",
                        "O",
                        "O",
                        "O",
                        "O",
                        "O",
                        "O",
                        "O",
                        "O",
                        "O",
                        "O",
                        "O",
                        "O",
                        "O",
                        "O",
                        "O",
                        "O",
                        "O",
                        "O",
                        "O",
                        "O"
                    ]
                ],
                "triggers": [
                    "{'words': 'Please leave', 'indices': '4 5'}",
                    "{'words': 'Please estimate', 'indices': '30 31'}"
                ],
                "extras": [
                    "",
                    ""
                ]
            },
            "Deliver_Action_Data": {
                "labels": [
                    [
                        "O",
                        "O",
                        "O",
                        "O",
                        "O",
                        "O",
                        "O",
                        "O",
                        "O",
                        "O",
                        "O",
                        "O",
                        "O",
                        "O",
                        "O",
                        "O",
                        "O",
                        "O",
                        "O",
                        "O",
                        "O",
                        "O",
                        "O",
                        "O",
                        "O",
                        "O",
                        "O",
                        "O",
                        "O",
                        "O",
                        "O",
                        "O",
                        "O",
                        "O",
                        "O",
                        "O",
                        "O",
                        "O",
                        "O",
                        "O",
                        "O",
                        "O",
                        "O",
                        "O",
                        "Deliver_Action_Data:B-Action Members",
                        "Deliver_Action_Data:B-Action Description",
                        "Deliver_Action_Data:I-Action Description",
                        "Deliver_Action_Data:I-Action Description",
                        "Deliver_Action_Data:I-Action Description",
                        "Deliver_Action_Data:I-Action Description",
                        "Deliver_Action_Data:I-Action Description",
                        "Deliver_Action_Data:I-Action Description",
                        "Deliver_Action_Data:I-Action Description",
                        "Deliver_Action_Data:I-Action Description",
                        "Deliver_Action_Data:I-Action Description",
                        "Deliver_Action_Data:I-Action Description",
                        "Deliver_Action_Data:I-Action Description",
                        "Deliver_Action_Data:I-Action Description",
                        "Deliver_Action_Data:I-Action Description",
                        "Deliver_Action_Data:I-Action Description",
                        "Deliver_Action_Data:I-Action Description",
                        "Deliver_Action_Data:I-Action Description",
                        "Deliver_Action_Data:I-Action Description",
                        "Deliver_Action_Data:I-Action Description",
                        "O",
                        "O",
                        "O",
                        "O",
                        "O",
                        "O",
                        "O"
                    ]
                ],
                "triggers": [
                    "{'words': 'would like to unload', 'indices': '45 46 47 48'}"
                ],
                "extras": [
                    "Deliver Confirmation : "
                ]
            }
        },
        "turn_1": {
            "Deliver_Data": {
                "labels": [
                    [
                        "O",
                        "Deliver_Data:B-Deliver members",
                        "O",
                        "Deliver_Data:B-Data idString",
                        "Deliver_Data:I-Data idString",
                        "Deliver_Data:I-Data idString",
                        "Deliver_Data:B-Data Value",
                        "Deliver_Data:I-Data Value",
                        "O",
                        "O",
                        "O",
                        "O",
                        "O",
                        "O",
                        "O",
                        "O",
                        "O",
                        "O",
                        "O",
                        "O",
                        "O",
                        "O",
                        "O",
                        "O",
                        "O",
                        "O",
                        "O",
                        "O",
                        "O",
                        "O",
                        "O",
                        "O",
                        "O",
                        "O",
                        "O",
                        "O",
                        "O",
                        "O",
                        "O",
                        "O",
                        "O",
                        "O",
                        "O",
                        "O",
                        "O",
                        "O",
                        "O",
                        "O",
                        "O",
                        "O",
                        "O",
                        "O",
                        "O",
                        "O",
                        "O",
                        "O",
                        "O",
                        "O",
                        "O",
                        "O",
                        "O",
                        "O",
                        "O",
                        "O",
                        "O",
                        "O",
                        "O",
                        "O",
                        "O",
                        "O",
                        "O",
                        "O",
                        "O",
                        "O",
                        "O",
                        "O",
                        "O",
                        "O",
                        "O",
                        "O",
                        "O",
                        "O",
                        "O",
                        "O",
                        "O",
                        "O",
                        "O",
                        "O",
                        "O",
                        "O",
                        "O",
                        "O",
                        "O",
                        "O",
                        "O",
                        "O",
                        "O",
                        "O",
                        "O",
                        "O",
                        "O",
                        "O",
                        "O",
                        "O",
                        "O",
                        "O",
                        "O",
                        "O",
                        "O",
                        "O",
                        "O",
                        "O",
                        "O",
                        "O"
                    ]
                ],
                "triggers": [
                    "{'words': 'Minimum quantity heel', 'indices': '3 4 5'}"
                ],
                "extras": [
                    "Deliver Confirmation : "
                ]
            },
            "Deliver_Action_Data": {
                "labels": [
                    [
                        "O",
                        "O",
                        "O",
                        "O",
                        "O",
                        "O",
                        "O",
                        "O",
                        "O",
                        "O",
                        "O",
                        "O",
                        "O",
                        "O",
                        "O",
                        "O",
                        "O",
                        "O",
                        "O",
                        "O",
                        "O",
                        "O",
                        "O",
                        "O",
                        "O",
                        "O",
                        "O",
                        "O",
                        "O",
                        "O",
                        "O",
                        "O",
                        "O",
                        "O",
                        "O",
                        "O",
                        "O",
                        "O",
                        "O",
                        "O",
                        "O",
                        "O",
                        "O",
                        "O",
                        "O",
                        "O",
                        "O",
                        "O",
                        "O",
                        "O",
                        "O",
                        "O",
                        "O",
                        "O",
                        "O",
                        "O",
                        "O",
                        "O",
                        "O",
                        "O",
                        "O",
                        "O",
                        "O",
                        "O",
                        "O",
                        "O",
                        "O",
                        "O",
                        "O",
                        "Deliver_Action_Data:B-Action Members",
                        "Deliver_Action_Data:B-Action Description",
                        "Deliver_Action_Data:I-Action Description",
                        "Deliver_Action_Data:I-Action Description",
                        "Deliver_Action_Data:I-Action Description",
                        "Deliver_Action_Data:I-Action Description",
                        "Deliver_Action_Data:I-Action Description",
                        "Deliver_Action_Data:I-Action Description",
                        "Deliver_Action_Data:I-Action Description",
                        "Deliver_Action_Data:I-Action Description",
                        "Deliver_Action_Data:I-Action Description",
                        "Deliver_Action_Data:I-Action Description",
                        "Deliver_Action_Data:I-Action Description",
                        "Deliver_Action_Data:I-Action Description",
                        "Deliver_Action_Data:I-Action Description",
                        "Deliver_Action_Data:I-Action Description",
                        "Deliver_Action_Data:I-Action Description",
                        "Deliver_Action_Data:I-Action Description",
                        "Deliver_Action_Data:I-Action Description",
                        "O",
                        "O",
                        "O",
                        "O",
                        "O",
                        "O",
                        "O",
                        "O",
                        "O",
                        "O",
                        "O",
                        "O",
                        "O",
                        "O",
                        "O",
                        "O",
                        "O",
                        "O",
                        "O",
                        "O",
                        "O",
                        "O",
                        "O",
                        "O",
                        "O",
                        "O"
                    ]
                ],
                "triggers": [
                    "{'words': 'will start loading', 'indices': '70 71 72'}"
                ],
                "extras": [
                    "Deliver Confirmation : "
                ]
            }
        },
        "turn_2": {
            "Request_Action": {
                "labels": [
                    [
                        "O",
                        "O",
                        "O",
                        "O",
                        "O",
                        "O",
                        "O",
                        "O",
                        "O",
                        "O",
                        "O",
                        "O",
                        "Request_Action:B-Action Description",
                        "Request_Action:I-Action Description",
                        "Request_Action:I-Action Description",
                        "O",
                        "O",
                        "O",
                        "O",
                        "O"
                    ]
                ],
                "triggers": [
                    "{'words': 'Please plan', 'indices': '12 13'}"
                ],
                "extras": [
                    ""
                ]
            }
        }
    },
    "sentences": [
        [
            "Captain",
            "Bentzr",
            "?",
            "d-",
            "Please",
            "leave",
            "a",
            "heel",
            "of",
            "LNG",
            "on",
            "board",
            "the",
            "vessel",
            "sufficient",
            "to",
            "reach",
            "the",
            "next",
            "loading",
            "in",
            "Qalhat",
            "on",
            "July",
            "5",
            "in",
            "load",
            "ready",
            "condition",
            ".",
            "Please",
            "estimate",
            "the",
            "volume",
            "you",
            "will",
            "require",
            "and",
            "revert",
            ",",
            "keeping",
            "in",
            "mind",
            "that",
            "we",
            "would",
            "like",
            "to",
            "unload",
            "as",
            "much",
            "as",
            "possible",
            "on",
            "June",
            "9",
            "at",
            "Lake",
            "Charles",
            "within",
            "the",
            "parameters",
            "outlined",
            "above",
            ".",
            "Thanks",
            "and",
            "regards",
            ",",
            "Dan",
            "Masters"
        ],
        [
            "Dear",
            "Sir",
            ";",
            "Minimum",
            "quantity",
            "heel",
            "3200",
            "m3",
            ".",
            "This",
            "will",
            "theoretically",
            "be",
            "sufficient",
            "for",
            "having",
            "all",
            "5",
            "tanks",
            "ready",
            "for",
            "loading",
            "in",
            "Qalhat",
            "5th",
            "July",
            ".",
            "As",
            "no",
            "empiric",
            "data",
            "is",
            "available",
            ",",
            "in",
            "stead",
            "of",
            "taking",
            "more",
            "to",
            "be",
            "on",
            "the",
            "safe",
            "side",
            ",",
            "I",
            "suggest",
            "that",
            "we",
            ",",
            "if",
            "found",
            "necessary",
            ",",
            "reduce",
            "number",
            "of",
            "tanks=",
            "ready",
            "for",
            "loading",
            ",",
            "to",
            "let",
            "say",
            "3",
            ".",
            "Then",
            "we",
            "will",
            "start",
            "loading",
            "at",
            "these",
            "three",
            "with",
            "somewhat",
            "reduced",
            "rate",
            ",",
            "and",
            "cooling",
            "down",
            "the",
            "two",
            "others",
            "simultanously",
            ".",
            "This",
            "operation",
            "should",
            "not",
            "delay",
            "us",
            "more",
            "than",
            "4",
            "hours",
            ".",
            "The",
            "other",
            "alternative",
            "is",
            "to",
            "take",
            "3600",
            "m3",
            ".",
            "Brgds",
            "Knut",
            "Bentzr",
            "?",
            "d"
        ],
        [
            "I",
            "think",
            "your",
            "plan",
            "outlined",
            "for",
            "keeping",
            "3,200",
            "m3",
            "looks",
            "good",
            ".",
            "Please",
            "plan",
            "accordingly",
            ".",
            "Regards",
            ",",
            "Dan",
            "Masters"
        ]
    ]
}